relativeNeighborhoodGraph/__init__.py
relativeNeighborhoodGraph/returnRNG.py
relativeNeighborhoodGraph-0.0.1.dist-info/LICENSE
relativeNeighborhoodGraph-0.0.1.dist-info/METADATA
relativeNeighborhoodGraph-0.0.1.dist-info/WHEEL
relativeNeighborhoodGraph-0.0.1.dist-info/top_level.txt
relativeNeighborhoodGraph-0.0.1.dist-info/RECORD
