Metadata-Version: 2.1
Name: relativeNeighborhoodGraph
Version: 0.0.1
Summary: Compute the Relative Neighborhood Graph from a distance matrix
Home-page: https://github.com/temcavanagh/relativeNeighborhoodGraph
Author: T Cavanagh
Author-email: cavanaghtd@gmail.com
License: UNKNOWN
Platform: UNKNOWN
Classifier: Programming Language :: Python :: 3
Classifier: License :: OSI Approved :: MIT License
Classifier: Operating System :: OS Independent
Requires-Python: >=3.6
License-File: LICENSE
